tasq_cli/.DS_Store
tasq_cli/__init__.py
tasq_cli/__main__.py
tasq_cli/credentials.py
tasq_cli/db.py
tasq_cli/export_files.py
tasq_cli/jobs.py
tasq_cli/main.py
tasq_cli/projects.py
tasq_cli/server.py
tasq_cli/settings.py
tasq_cli/source_files.py
tasq_cli/tags.py
tasq_cli/upload.py
tasq_cli/utils.py
tasq_cli-1.0.42.dist-info/METADATA
tasq_cli-1.0.42.dist-info/WHEEL
tasq_cli-1.0.42.dist-info/entry_points.txt
tasq_cli-1.0.42.dist-info/RECORD
