Metadata-Version: 2.1
Name: tasq_cli
Version: 1.0.42
Summary: The command line tool for tasq.ai.
Author: tasq.ai
Author-email: info@tasq.ai
Requires-Python: >=3.6,<4.0
Classifier: Programming Language :: Python :: 3
Classifier: Programming Language :: Python :: 3.6
Classifier: Programming Language :: Python :: 3.7
Classifier: Programming Language :: Python :: 3.8
Classifier: Programming Language :: Python :: 3.9
Classifier: Programming Language :: Python :: 3.10
Classifier: Programming Language :: Python :: 3.11
Classifier: Programming Language :: Python :: 3.12
Requires-Dist: Django (>=3.1.2,<4.0.0)
Requires-Dist: altgraph (>=0.17,<0.18)
Requires-Dist: boto3 (>=1.16.4,<2.0.0)
Requires-Dist: botocore (>=1.19.4,<2.0.0)
Requires-Dist: docutils (>=0.16,<0.17)
Requires-Dist: jmespath (>=0.10.0,<0.11.0)
Requires-Dist: pillow (>=8.0.1,<9.0.0)
Requires-Dist: pyinstaller (>=4.0,<5.0)
Requires-Dist: pyinstaller-hooks-contrib (>=2020.9,<2021.0)
Requires-Dist: python-dateutil (>=2.8.1,<3.0.0)
Requires-Dist: python-dotenv (>=0.14.0,<0.15.0)
Requires-Dist: requests (>=2.23.0,<3.0.0)
Requires-Dist: s3transfer (>=0.3.3,<0.4.0)
Requires-Dist: urllib3 (>=1.25.11,<2.0.0)
